Metadata-Version: 1.1
Name: hflossk
Version: 0.5.9
Summary: HFOSS course materials via flask
Home-page: UNKNOWN
Author: Remy DeCausemaker
Author-email: remyd@civx.us
License: GPLv3+
Keywords: courseware
Platform: UNKNOWN
Classifier: Natural Language :: English
Classifier: Operating System :: POSIX :: Linux
Classifier: Programming Language :: Python :: 2.7
